dataspace/__init__.py
dataspace/build_doc.py
dataspace/types.py
dataspace/calculations/__init__.py
dataspace/calculations/diff.py
dataspace/calculations/percent.py
dataspace/calculations/regression.py
dataspace/calculations/var.py
dataspace/charts/__init__.py
dataspace/charts/base.py
dataspace/charts/altair/__init__.py
dataspace/charts/altair/altair.py
dataspace/charts/altair/charts.py
dataspace/charts/bokeh/__init__.py
dataspace/charts/bokeh/bokeh.py
dataspace/charts/bokeh/charts.py
dataspace/clean/__init__.py
dataspace/clean/convert.py
dataspace/clean/dates.py
dataspace/clean/nulls.py
dataspace/clean/values.py
dataspace/core/__init__.py
dataspace/core/core.py
dataspace/core/env.py
dataspace/core/load.py
dataspace/count/__init__.py
dataspace/count/count.py
dataspace/info/__init__.py
dataspace/info/view.py
dataspace/io/__init__.py
dataspace/io/export/__init__.py
dataspace/report/__init__.py
dataspace/report/base.py
dataspace/transform/__init__.py
dataspace/transform/dataframe.py
dataspace/transform/resample.py
dataspace/utils/__init__.py
dataspace/utils/colors.py
dataspace/utils/messages.py
tests/__init__.py
tests/base.py
tests/test_clean.py
tests/test_count.py
tests/test_init.py
tests/test_select.py
tests/test_transform.py
dataspace-0.0.13.dist-info/LICENSE
dataspace-0.0.13.dist-info/METADATA
dataspace-0.0.13.dist-info/WHEEL
dataspace-0.0.13.dist-info/top_level.txt
dataspace-0.0.13.dist-info/RECORD
