Metadata-Version: 2.1
Name: dataspace
Version: 0.0.13
Summary: Data wrangling and visualization
Home-page: https://github.com/synw/dataspace
Download-URL: https://github.com/synw/dataspace/releases/tag/0.0.13
Author: synw
Author-email: synwe@yahoo.com
Keywords: data_visualization,data_exploration,charts
Classifier: Development Status :: 3 - Alpha
Classifier: Intended Audience :: Developers
Classifier: License :: OSI Approved :: MIT License
Classifier: Programming Language :: Python :: 3.10
License-File: LICENSE
Requires-Dist: polars[numpy,pandas,pyarrow]
Requires-Dist: altair (>=5.0.0rc1)
Requires-Dist: holoviews
Requires-Dist: bokeh
